pathintegrate/__init__.py
pathintegrate/app.py
pathintegrate/pathintegrate.py
pathintegrate/plot.py
pathintegrate/utils.py
pathintegrate/data/ReactomePathwaysRelation.txt
pathintegrate/data/Reactome_Homo_sapiens_pathways_multiomics_R85.gmt
pathintegrate/data/copd_pvals.csv
pathintegrate/data/metabolomics_example.csv
pathintegrate/data/proteomics_example.csv
PathIntegrate-1.0.2.dist-info/LICENSE
PathIntegrate-1.0.2.dist-info/METADATA
PathIntegrate-1.0.2.dist-info/WHEEL
PathIntegrate-1.0.2.dist-info/top_level.txt
PathIntegrate-1.0.2.dist-info/RECORD
