Metadata-Version: 2.1
Name: PathIntegrate
Version: 1.0.2
Summary: PathIntegrate: multivariate modelling approaches for pathway-based muti-omics integration
Home-page: https://github.com/cwieder/PathIntegrate
Author: Cecilia Wieder
Author-email: cw2019@ic.ac.uk
License: GNU 3.0
Classifier: Programming Language :: Python
Classifier: Programming Language :: Python :: 3
Classifier: Programming Language :: Python :: 3.10
License-File: LICENSE
Requires-Dist: cmcrameri
Requires-Dist: dash
Requires-Dist: dash-bootstrap-components
Requires-Dist: dash-cytoscape
Requires-Dist: datauri
Requires-Dist: mbpls
Requires-Dist: scikit-learn
Requires-Dist: networkx
Requires-Dist: setuptools
Requires-Dist: sspa>=1.0.1
Requires-Dist: statsmodels
Requires-Dist: svgwrite
